odoo/addons/partner_prospect/README.rst
odoo/addons/partner_prospect/__init__.py
odoo/addons/partner_prospect/__manifest__.py
odoo/addons/partner_prospect/i18n/de.po
odoo/addons/partner_prospect/i18n/es.po
odoo/addons/partner_prospect/i18n/fr.po
odoo/addons/partner_prospect/i18n/partner_prospect.pot
odoo/addons/partner_prospect/i18n/sl.po
odoo/addons/partner_prospect/i18n/zh_CN.po
odoo/addons/partner_prospect/models/__init__.py
odoo/addons/partner_prospect/models/res_partner.py
odoo/addons/partner_prospect/readme/CONTRIBUTORS.rst
odoo/addons/partner_prospect/readme/DESCRIPTION.rst
odoo/addons/partner_prospect/static/description/icon.png
odoo/addons/partner_prospect/static/description/index.html
odoo/addons/partner_prospect/tests/__init__.py
odoo/addons/partner_prospect/tests/test_partner_prospect.py
odoo/addons/partner_prospect/views/res_partner_view.xml
odoo13_addon_partner_prospect-13.0.1.0.1.dev7.dist-info/METADATA
odoo13_addon_partner_prospect-13.0.1.0.1.dev7.dist-info/WHEEL
odoo13_addon_partner_prospect-13.0.1.0.1.dev7.dist-info/top_level.txt
odoo13_addon_partner_prospect-13.0.1.0.1.dev7.dist-info/RECORD
